fleck/__init__.py
fleck/_astropy_init.py
fleck/conftest.py
fleck/core.py
fleck/version.py
fleck/data/README.rst
fleck/data/stsp_double_transit.txt
fleck/data/stsp_rotation.txt
fleck/data/stsp_single_transit.txt
fleck/extern/__init__.py
fleck/tests/__init__.py
fleck/tests/coveragerc
fleck/tests/setup_package.py
fleck/tests/test_core.py
fleck/utils/__init__.py
fleck/utils/tests/__init__.py
fleck-0.0.dev72.dist-info/LICENSE
fleck-0.0.dev72.dist-info/METADATA
fleck-0.0.dev72.dist-info/WHEEL
fleck-0.0.dev72.dist-info/entry_points.txt
fleck-0.0.dev72.dist-info/top_level.txt
fleck-0.0.dev72.dist-info/RECORD
